todomd/__init__.py
todomd/__main__.py
tdmd-0.0.2.dist-info/LICENSE
tdmd-0.0.2.dist-info/METADATA
tdmd-0.0.2.dist-info/WHEEL
tdmd-0.0.2.dist-info/top_level.txt
tdmd-0.0.2.dist-info/RECORD
