Metadata-Version: 2.1
Name: tdmd
Version: 0.0.2
Summary: Manage your tasks using the command line interface and view your plans in a visually appealing markdown file.
Author-email: Alex Zolotarov <alex@zolotarov.me>
Requires-Python: >=3.9
License-File: LICENSE
Requires-Dist: fire
